LICENSE
README.md
setup.py
AdvancedVisualizations/Pareto.py
AdvancedVisualizations/__init__.py
AdvancedVisualizations.egg-info/PKG-INFO
AdvancedVisualizations.egg-info/SOURCES.txt
AdvancedVisualizations.egg-info/dependency_links.txt
AdvancedVisualizations.egg-info/top_level.txt