Metadata-Version: 2.1
Name: AdvancedVisualizations
Version: 0.0.1
Summary: AdvancedVisualizations is a library that provides different types of plots.
Author: Peter Jachim
License-File: LICENSE
